odoo10_addon_shopinvader_import_image-10.0.1.0.2-py3.8-nspkg.pth
odoo/addons/shopinvader_import_image/README.rst
odoo/addons/shopinvader_import_image/__init__.py
odoo/addons/shopinvader_import_image/__manifest__.py
odoo/addons/shopinvader_import_image/models/__init__.py
odoo/addons/shopinvader_import_image/models/import_image.py
odoo/addons/shopinvader_import_image/readme/CONTRIBUTORS.rst
odoo/addons/shopinvader_import_image/readme/DESCRIPTION.rst
odoo/addons/shopinvader_import_image/static/description/index.html
odoo/addons/shopinvader_import_image/views/import_product_image_view.xml
odoo10_addon_shopinvader_import_image-10.0.1.0.2.dist-info/METADATA
odoo10_addon_shopinvader_import_image-10.0.1.0.2.dist-info/WHEEL
odoo10_addon_shopinvader_import_image-10.0.1.0.2.dist-info/namespace_packages.txt
odoo10_addon_shopinvader_import_image-10.0.1.0.2.dist-info/top_level.txt
odoo10_addon_shopinvader_import_image-10.0.1.0.2.dist-info/RECORD
