Metadata-Version: 2.1
Name: odoo10-addon-shopinvader-import-image
Version: 10.0.1.0.2
Summary: Import product images
Home-page: https://www.akretion.com
Author: Sylvain Calador
License: AGPL-3
Platform: UNKNOWN
Classifier: Programming Language :: Python
Classifier: Framework :: Odoo
Classifier: License :: OSI Approved :: GNU Affero General Public License v3
Requires-Python: ~=2.7
Requires-Dist: odoo10-addon-shopinvader-image
Requires-Dist: odoo (<10.1dev,>=10.0)
Requires-Dist: python-magic
Requires-Dist: validators
